protein_mcp/__init__.py
protein_mcp/server.py
protein_mcp/tools.py
protein_mcp/utils.py
protein_mcp-0.1.5.dist-info/licenses/LICENSE
protein_mcp-0.1.5.dist-info/METADATA
protein_mcp-0.1.5.dist-info/WHEEL
protein_mcp-0.1.5.dist-info/entry_points.txt
protein_mcp-0.1.5.dist-info/top_level.txt
protein_mcp-0.1.5.dist-info/RECORD
