Metadata-Version: 2.4
Name: protein-mcp
Version: 0.1.5
Summary: FastMCP-based protein data access tools for bioinformatics research
Author-email: gqy20 <qingyu_ge@foxmail.com>
License-Expression: MIT
Project-URL: Homepage, https://github.com/gqy20/protein-mcp
Project-URL: Repository, https://github.com/gqy20/protein-mcp.git
Project-URL: Bug Tracker, https://github.com/gqy20/protein-mcp/issues
Project-URL: Changelog, https://github.com/gqy20/protein-mcp/blob/main/CHANGELOG.md
Keywords: protein,mcp,bioinformatics,rcsb,pdb,structure,fastmcp
Requires-Python: >=3.10
License-File: LICENSE
Requires-Dist: fastmcp>=2.12.0
Requires-Dist: requests>=2.28.0
Requires-Dist: urllib3>=1.26.0
Provides-Extra: dev
Requires-Dist: pytest>=8.0.0; extra == "dev"
Requires-Dist: pytest-asyncio>=0.24.0; extra == "dev"
Requires-Dist: pytest-cov>=4.0.0; extra == "dev"
Requires-Dist: black==24.10.0; extra == "dev"
Requires-Dist: ruff>=0.1.0; extra == "dev"
Requires-Dist: mypy>=1.0.0; extra == "dev"
Requires-Dist: isort>=5.12.0; extra == "dev"
Dynamic: license-file
